README.md
setup.py
domi/__about__.py
domi/__init__.py
domi/core.py
domi.egg-info/PKG-INFO
domi.egg-info/SOURCES.txt
domi.egg-info/dependency_links.txt
domi.egg-info/requires.txt
domi.egg-info/top_level.txt
domi/datasource/__init__.py
domi/environment/__init__.py
domi/environment/graph.py
domi/environment/w7x.py
domi/node/__init__.py
domi/node/node.py
domi/node/heating/__init__.py
domi/node/mhd/__init__.py
domi/node/mhd/vmec/__init__.py
domi/node/mhd/vmec/config.py
domi/node/mhd/vmec/test.py
domi/node/mhd/vmec/vmec.py
domi/node/tracing/__init__.py
domi/node/tracing/flt.py
domi/node/turbulence/__init__.py
domi/state/__init__.py
domi/util/__init__.py