Metadata-Version: 2.1
Name: domi
Version: 0.1.0.dev0
Summary: Generic framework (gr. domi) for modeling physics environements
Home-page: https://gitlab.mpcdf.mpg.de/dboe/domi
Author: Daniel Böckenhoff and Anderea Merlo
Author-email: dboe@ipp.mpg.de, amerlo@ipp.mpg.de
License: Apache Software License
Project-URL: Documentation, https://gitlab.mpcdf.mpg.de/dboe/domi
Project-URL: Source, https://gitlab.mpcdf.mpg.de/dboe/domi
Keywords: environment,forward modeling,graph,node,
Platform: UNKNOWN
Classifier: Development Status :: 3 - Alpha
Classifier: License :: OSI Approved :: Apache Software License
Classifier: Programming Language :: Python
Classifier: Programming Language :: Python :: 3
Classifier: Programming Language :: Python :: 3.2
Classifier: Programming Language :: Python :: 3.3
Classifier: Programming Language :: Python :: 3.4
Classifier: Programming Language :: Python :: 3.5
Classifier: Programming Language :: Python :: 3.6
Classifier: Programming Language :: Python :: 3.7
Classifier: Programming Language :: Python :: 3.8
Requires-Python: >=3.0
